pyrexx/__init__.py
pyrexx/background_colors.py
pyrexx/exceptions/__init__.py
pyrexx/exceptions/pyrexx_exceptions.py
pyrexx/rexx/__init__.py
pyrexx/rexx/rexx_code.py
pyrexx/rexx/rexx_file.py
pyrexx/rexx/rexx_sub_routine.py
pyrexx/rexx/source_code.py
pyrexx/rexx/statements/__init__.py
pyrexx/rexx/statements/docstring_statement.py
pyrexx/rexx/statements/include_statement.py
pyrexx/rexx/statements/rexx_statement.py
pyrexx/utilities/__init__.py
pyrexx/utilities/logger.py
pyrexx-0.4.3.dist-info/LICENSE
pyrexx-0.4.3.dist-info/METADATA
pyrexx-0.4.3.dist-info/WHEEL
pyrexx-0.4.3.dist-info/top_level.txt
pyrexx-0.4.3.dist-info/RECORD
