Metadata-Version: 2.1
Name: pyrexx
Version: 0.4.3
Summary: Python library that enables parsing and analysis of REXX source code
Home-page: UNKNOWN
Author: Guilherme Cartier
License: UNKNOWN
Platform: UNKNOWN
Requires-Python: >=3.6
